{
    "graph": [
        {
            "author": " Phil Weir",
            "cards": [
                {
                    "active": true,
                    "cardid": "5b8b4480-9687-11ee-8782-0242ac140006",
                    "component_id": "f05e4d3a-53c1-11e8-b0ea-784f435179ea",
                    "config": null,
                    "constraints": [],
                    "cssclass": null,
                    "description": null,
                    "graph_id": "5b8b4084-9687-11ee-8782-0242ac140006",
                    "helpenabled": false,
                    "helptext": {
                        "en": ""
                    },
                    "helptitle": {
                        "en": ""
                    },
                    "instructions": {
                        "en": ""
                    },
                    "name": {
                        "en": "Title"
                    },
                    "nodegroup_id": "5b8b43ae-9687-11ee-8782-0242ac140006",
                    "sortorder": null,
                    "source_identifier_id": null,
                    "visible": true
                },
                {
                    "active": true,
                    "cardid": "6a87eecc-d37a-4249-9506-a7e72d7c5269",
                    "component_id": "f05e4d3a-53c1-11e8-b0ea-784f435179ea",
                    "config": null,
                    "constraints": [],
                    "cssclass": null,
                    "description": null,
                    "graph_id": "5b8b4084-9687-11ee-8782-0242ac140006",
                    "helpenabled": false,
                    "helptext": {
                        "en": ""
                    },
                    "helptitle": {
                        "en": ""
                    },
                    "instructions": {
                        "en": ""
                    },
                    "name": {
                        "en": "Member Definition"
                    },
                    "nodegroup_id": "2f94332c-9688-11ee-8782-0242ac140006",
                    "sortorder": null,
                    "source_identifier_id": null,
                    "visible": true
                }
            ],
            "cards_x_nodes_x_widgets": [
                {
                    "card_id": "5b8b4480-9687-11ee-8782-0242ac140006",
                    "config": {
                        "defaultValue": {
                            "en": {
                                "direction": "ltr",
                                "value": ""
                            }
                        },
                        "i18n_properties": [
                            "placeholder"
                        ],
                        "label": "Title Text",
                        "maxLength": null,
                        "placeholder": {
                            "en": "Enter text"
                        },
                        "uneditable": false,
                        "width": "100%"
                    },
                    "id": "5b8b47fa-9687-11ee-8782-0242ac140006",
                    "label": {
                        "en": "Title Text"
                    },
                    "node_id": "5b8b46b0-9687-11ee-8782-0242ac140006",
                    "sortorder": 0,
                    "source_identifier_id": null,
                    "visible": true,
                    "widget_id": "10000000-0000-0000-0000-000000000001"
                }
            ],
            "color": "#798031",
            "config": {},
            "deploymentdate": null,
            "deploymentfile": null,
            "description": {
                "en": "A grouping of resources, possibly nested, for purposes of co-management."
            },
            "edges": [
                {
                    "description": null,
                    "domainnode_id": "5b8b43ae-9687-11ee-8782-0242ac140006",
                    "edgeid": "5b8b804e-9687-11ee-8782-0242ac140006",
                    "graph_id": "5b8b4084-9687-11ee-8782-0242ac140006",
                    "name": null,
                    "ontologyproperty": null,
                    "rangenode_id": "5b8b46b0-9687-11ee-8782-0242ac140006",
                    "source_identifier_id": null
                },
                {
                    "description": null,
                    "domainnode_id": "5b8b475a-9687-11ee-8782-0242ac140006",
                    "edgeid": "5b8b80ee-9687-11ee-8782-0242ac140006",
                    "graph_id": "5b8b4084-9687-11ee-8782-0242ac140006",
                    "name": null,
                    "ontologyproperty": null,
                    "rangenode_id": "5b8b43ae-9687-11ee-8782-0242ac140006",
                    "source_identifier_id": null
                },
                {
                    "description": null,
                    "domainnode_id": "5b8b475a-9687-11ee-8782-0242ac140006",
                    "edgeid": "81bc73a1-2a57-4769-8dcb-940dcc7b1264",
                    "graph_id": "5b8b4084-9687-11ee-8782-0242ac140006",
                    "name": null,
                    "ontologyproperty": null,
                    "rangenode_id": "2f94332c-9688-11ee-8782-0242ac140006",
                    "source_identifier_id": null
                }
            ],
            "functions_x_graphs": [
                {
                    "config": {
                        "descriptor_types": {
                            "description": {
                                "nodegroup_id": "",
                                "string_template": ""
                            },
                            "map_popup": {
                                "nodegroup_id": "",
                                "string_template": ""
                            },
                            "name": {
                                "nodegroup_id": "5b8b43ae-9687-11ee-8782-0242ac140006",
                                "string_template": "<Title Text>"
                            }
                        },
                        "triggering_nodegroups": []
                    },
                    "function_id": "60000000-0000-0000-0000-000000000001",
                    "graph_id": "5b8b4084-9687-11ee-8782-0242ac140006",
                    "id": "25c0b28c-8048-4af2-986b-137e4e43a01b"
                }
            ],
            "graphid": "5b8b4084-9687-11ee-8782-0242ac140006",
            "group_permissions": {},
            "has_unpublished_changes": true,
            "iconclass": "fa fa-cubes",
            "is_active": true,
            "is_copy_immutable": false,
            "isresource": true,
            "jsonldcontext": null,
            "name": {
                "en": "Logical Set"
            },
            "nodegroups": [
                {
                    "cardinality": "1",
                    "grouping_node_id": "2f94332c-9688-11ee-8782-0242ac140006",
                    "legacygroupid": null,
                    "nodegroupid": "2f94332c-9688-11ee-8782-0242ac140006",
                    "parentnodegroup_id": null
                },
                {
                    "cardinality": "1",
                    "grouping_node_id": "5b8b43ae-9687-11ee-8782-0242ac140006",
                    "legacygroupid": null,
                    "nodegroupid": "5b8b43ae-9687-11ee-8782-0242ac140006",
                    "parentnodegroup_id": null
                }
            ],
            "nodes": [
                {
                    "alias": "member_definition",
                    "config": {
                    },
                    "datatype": "non-localized-string",
                    "description": null,
                    "exportable": false,
                    "fieldname": null,
                    "graph_id": "5b8b4084-9687-11ee-8782-0242ac140006",
                    "hascustomalias": false,
                    "is_collector": true,
                    "is_immutable": false,
                    "isrequired": true,
                    "issearchable": false,
                    "istopnode": false,
                    "name": "Member Definition",
                    "nodegroup_id": "2f94332c-9688-11ee-8782-0242ac140006",
                    "nodeid": "2f94332c-9688-11ee-8782-0242ac140006",
                    "ontologyclass": null,
                    "parentproperty": null,
                    "sortorder": 0,
                    "source_identifier_id": null,
                    "sourcebranchpublication_id": null
                },
                {
                    "alias": "title",
                    "config": {
                        "en": ""
                    },
                    "datatype": "semantic",
                    "description": null,
                    "exportable": false,
                    "fieldname": null,
                    "graph_id": "5b8b4084-9687-11ee-8782-0242ac140006",
                    "hascustomalias": false,
                    "is_collector": true,
                    "is_immutable": false,
                    "isrequired": true,
                    "issearchable": true,
                    "istopnode": false,
                    "name": "Title",
                    "nodegroup_id": "5b8b43ae-9687-11ee-8782-0242ac140006",
                    "nodeid": "5b8b43ae-9687-11ee-8782-0242ac140006",
                    "ontologyclass": null,
                    "parentproperty": null,
                    "sortorder": 0,
                    "source_identifier_id": null,
                    "sourcebranchpublication_id": null
                },
                {
                    "alias": "title_text",
                    "config": {
                        "en": ""
                    },
                    "datatype": "string",
                    "description": null,
                    "exportable": true,
                    "fieldname": "set_title",
                    "graph_id": "5b8b4084-9687-11ee-8782-0242ac140006",
                    "hascustomalias": false,
                    "is_collector": false,
                    "is_immutable": false,
                    "isrequired": true,
                    "issearchable": true,
                    "istopnode": false,
                    "name": "Title Text",
                    "nodegroup_id": "5b8b43ae-9687-11ee-8782-0242ac140006",
                    "nodeid": "5b8b46b0-9687-11ee-8782-0242ac140006",
                    "ontologyclass": null,
                    "parentproperty": null,
                    "sortorder": 0,
                    "source_identifier_id": null,
                    "sourcebranchpublication_id": null
                },
                {
                    "alias": "logical_set",
                    "config": {
                        "en": ""
                    },
                    "datatype": "semantic",
                    "description": "",
                    "exportable": false,
                    "fieldname": null,
                    "graph_id": "5b8b4084-9687-11ee-8782-0242ac140006",
                    "hascustomalias": false,
                    "is_collector": false,
                    "is_immutable": false,
                    "isrequired": false,
                    "issearchable": true,
                    "istopnode": true,
                    "name": "Logical Set",
                    "nodegroup_id": null,
                    "nodeid": "5b8b475a-9687-11ee-8782-0242ac140006",
                    "ontologyclass": null,
                    "parentproperty": "",
                    "sortorder": 0,
                    "source_identifier_id": null,
                    "sourcebranchpublication_id": null
                }
            ],
            "ontology_id": null,
            "publication": {
                "graph_id": "5b8b4084-9687-11ee-8782-0242ac140006",
                "most_recent_edit_id": null,
                "notes": null,
                "publicationid": "6d9d83c6-9688-11ee-a81e-0242ac140006",
                "published_time": "2023-12-09T11:45:19.382"
            },
            "relatable_resource_model_ids": [],
            "resource_2_resource_constraints": [],
            "resource_instance_lifecycle": {
                "id": "7e3cce56-fbfb-4a4b-8e83-59b9f9e7cb75",
                "name": {
                    "en": "Standard"
                },
                "resource_instance_lifecycle_states": [
                    {
                        "action_label": {
                            "en": "Revert to Draft"
                        },
                        "can_delete_resource_instances": true,
                        "can_edit_resource_instances": true,
                        "id": "9375c9a7-dad2-4f14-a5c1-d7e329fdde4f",
                        "is_initial_state": true,
                        "name": {
                            "en": "Draft"
                        },
                        "next_resource_instance_lifecycle_states": [
                            "f75bb034-36e3-4ab4-8167-f520cf0b4c58"
                        ],
                        "previous_resource_instance_lifecycle_states": [],
                        "resource_instance_lifecycle_id": "7e3cce56-fbfb-4a4b-8e83-59b9f9e7cb75"
                    },
                    {
                        "action_label": {
                            "en": "Make Active"
                        },
                        "can_delete_resource_instances": false,
                        "can_edit_resource_instances": true,
                        "id": "f75bb034-36e3-4ab4-8167-f520cf0b4c58",
                        "is_initial_state": false,
                        "name": {
                            "en": "Active"
                        },
                        "next_resource_instance_lifecycle_states": [
                            "d95d9c0e-0e2c-4450-93a3-d788b91abcc8"
                        ],
                        "previous_resource_instance_lifecycle_states": [
                            "9375c9a7-dad2-4f14-a5c1-d7e329fdde4f"
                        ],
                        "resource_instance_lifecycle_id": "7e3cce56-fbfb-4a4b-8e83-59b9f9e7cb75"
                    },
                    {
                        "action_label": {
                            "en": "Retire"
                        },
                        "can_delete_resource_instances": false,
                        "can_edit_resource_instances": false,
                        "id": "d95d9c0e-0e2c-4450-93a3-d788b91abcc8",
                        "is_initial_state": false,
                        "name": {
                            "en": "Retired"
                        },
                        "next_resource_instance_lifecycle_states": [],
                        "previous_resource_instance_lifecycle_states": [
                            "f75bb034-36e3-4ab4-8167-f520cf0b4c58"
                        ],
                        "resource_instance_lifecycle_id": "7e3cce56-fbfb-4a4b-8e83-59b9f9e7cb75"
                    }
                ]
            },
            "root": {
                "alias": "logical_set",
                "config": {
                    "en": ""
                },
                "datatype": "semantic",
                "description": "",
                "exportable": false,
                "fieldname": null,
                "graph_id": "5b8b4084-9687-11ee-8782-0242ac140006",
                "hascustomalias": false,
                "is_collector": false,
                "is_immutable": false,
                "isrequired": false,
                "issearchable": true,
                "istopnode": true,
                "name": "Logical Set",
                "nodegroup_id": null,
                "nodeid": "5b8b475a-9687-11ee-8782-0242ac140006",
                "ontologyclass": null,
                "sortorder": 0,
                "source_identifier_id": null,
                "sourcebranchpublication_id": null
            },
            "slug": "logical_set",
            "source_identifier_id": null,
            "spatial_views": [],
            "subtitle": {
                "en": "Nestable collection of subject resources on which actors may have permissions."
            },
            "template_id": "50000000-0000-0000-0000-000000000001",
            "user_permissions": {},
            "version": ""
        }
    ],
    "metadata": {
        "db": "PostgreSQL 16.4 (Debian 16.4-1.pgdg110+1) on x86_64-pc-linux-gnu, compiled by gcc (Debian 10.2.1-6) 10.2.1 20210110, 64-bit",
        "git hash": "fatal: your current branch 'master' does not have any commits yet",
        "os": "Linux",
        "os version": "6.11.0-29-generic"
    }
}
